[
  {
    "id": "jp-bw2-red-collection-071/066",
    "name": "N - 071/066",
    "supertype": "Pokémon",
    "number": "071/066",
    "rarity": "Super Rare",
    "images": {
      "small": "https://tcgplayer-cdn.tcgplayer.com/product/600954_200w.jpg",
      "large": "https://tcgplayer-cdn.tcgplayer.com/product/600954_400w.jpg"
    },
    "tcgplayerId": "600954"
  },
  {
    "id": "jp-bw2-red-collection-070/066",
    "name": "Victini - 070/066",
    "supertype": "Pokémon",
    "number": "070/066",
    "rarity": "Super Rare",
    "images": {
      "small": "https://tcgplayer-cdn.tcgplayer.com/product/600974_200w.jpg",
      "large": "https://tcgplayer-cdn.tcgplayer.com/product/600974_400w.jpg"
    },
    "tcgplayerId": "600974"
  },
  {
    "id": "jp-bw2-red-collection-067/066",
    "name": "Virizion - 067/066",
    "supertype": "Pokémon",
    "number": "067/066",
    "rarity": "Super Rare",
    "images": {
      "small": "https://tcgplayer-cdn.tcgplayer.com/product/600976_200w.jpg",
      "large": "https://tcgplayer-cdn.tcgplayer.com/product/600976_400w.jpg"
    },
    "tcgplayerId": "600976"
  },
  {
    "id": "jp-bw2-red-collection-069/066",
    "name": "Cobalion - 069/066",
    "supertype": "Pokémon",
    "number": "069/066",
    "rarity": "Super Rare",
    "images": {
      "small": "https://tcgplayer-cdn.tcgplayer.com/product/600919_200w.jpg",
      "large": "https://tcgplayer-cdn.tcgplayer.com/product/600919_400w.jpg"
    },
    "tcgplayerId": "600919"
  },
  {
    "id": "jp-bw2-red-collection-052/066",
    "name": "Hydreigon",
    "supertype": "Pokémon",
    "number": "052/066",
    "rarity": "Rare",
    "images": {
      "small": "https://tcgplayer-cdn.tcgplayer.com/product/600943_200w.jpg",
      "large": "https://tcgplayer-cdn.tcgplayer.com/product/600943_400w.jpg"
    },
    "tcgplayerId": "600943"
  },
  {
    "id": "jp-bw2-red-collection-055/066",
    "name": "Cobalion - 055/066",
    "supertype": "Pokémon",
    "number": "055/066",
    "rarity": "Rare",
    "images": {
      "small": "https://tcgplayer-cdn.tcgplayer.com/product/600918_200w.jpg",
      "large": "https://tcgplayer-cdn.tcgplayer.com/product/600918_400w.jpg"
    },
    "tcgplayerId": "600918"
  },
  {
    "id": "jp-bw2-red-collection-044/066",
    "name": "Golett",
    "supertype": "Pokémon",
    "number": "044/066",
    "rarity": "Common",
    "images": {
      "small": "https://tcgplayer-cdn.tcgplayer.com/product/600939_200w.jpg",
      "large": "https://tcgplayer-cdn.tcgplayer.com/product/600939_400w.jpg"
    },
    "tcgplayerId": "600939"
  },
  {
    "id": "jp-bw2-red-collection-056/066",
    "name": "Axew",
    "supertype": "Pokémon",
    "number": "056/066",
    "rarity": "Common",
    "images": {
      "small": "https://tcgplayer-cdn.tcgplayer.com/product/600913_200w.jpg",
      "large": "https://tcgplayer-cdn.tcgplayer.com/product/600913_400w.jpg"
    },
    "tcgplayerId": "600913"
  },
  {
    "id": "jp-bw2-red-collection-050/066",
    "name": "Deino",
    "supertype": "Pokémon",
    "number": "050/066",
    "rarity": "Common",
    "images": {
      "small": "https://tcgplayer-cdn.tcgplayer.com/product/600925_200w.jpg",
      "large": "https://tcgplayer-cdn.tcgplayer.com/product/600925_400w.jpg"
    },
    "tcgplayerId": "600925"
  },
  {
    "id": "jp-bw2-red-collection-039/066",
    "name": "Archen",
    "supertype": "Pokémon",
    "number": "039/066",
    "rarity": "Uncommon",
    "images": {
      "small": "https://tcgplayer-cdn.tcgplayer.com/product/600911_200w.jpg",
      "large": "https://tcgplayer-cdn.tcgplayer.com/product/600911_400w.jpg"
    },
    "tcgplayerId": "600911"
  },
  {
    "id": "jp-bw2-red-collection-045/066",
    "name": "Golurk",
    "supertype": "Pokémon",
    "number": "045/066",
    "rarity": "Uncommon",
    "images": {
      "small": "https://tcgplayer-cdn.tcgplayer.com/product/600940_200w.jpg",
      "large": "https://tcgplayer-cdn.tcgplayer.com/product/600940_400w.jpg"
    },
    "tcgplayerId": "600940"
  },
  {
    "id": "jp-bw2-red-collection-009/066",
    "name": "Victini - 009/066",
    "supertype": "Pokémon",
    "number": "009/066",
    "rarity": "Rare",
    "images": {
      "small": "https://tcgplayer-cdn.tcgplayer.com/product/600973_200w.jpg",
      "large": "https://tcgplayer-cdn.tcgplayer.com/product/600973_400w.jpg"
    },
    "tcgplayerId": "600973"
  },
  {
    "id": "jp-bw2-red-collection-058/066",
    "name": "Haxorus",
    "supertype": "Pokémon",
    "number": "058/066",
    "rarity": "Rare",
    "images": {
      "small": "https://tcgplayer-cdn.tcgplayer.com/product/600941_200w.jpg",
      "large": "https://tcgplayer-cdn.tcgplayer.com/product/600941_400w.jpg"
    },
    "tcgplayerId": "600941"
  },
  {
    "id": "jp-bw2-red-collection-024/066",
    "name": "Kyurem",
    "supertype": "Pokémon",
    "number": "024/066",
    "rarity": "Rare",
    "images": {
      "small": "https://tcgplayer-cdn.tcgplayer.com/product/600946_200w.jpg",
      "large": "https://tcgplayer-cdn.tcgplayer.com/product/600946_400w.jpg"
    },
    "tcgplayerId": "600946"
  },
  {
    "id": "jp-bw2-red-collection-008/066",
    "name": "Virizion - 008/066",
    "supertype": "Pokémon",
    "number": "008/066",
    "rarity": "Rare",
    "images": {
      "small": "https://tcgplayer-cdn.tcgplayer.com/product/600975_200w.jpg",
      "large": "https://tcgplayer-cdn.tcgplayer.com/product/600975_400w.jpg"
    },
    "tcgplayerId": "600975"
  },
  {
    "id": "jp-bw2-red-collection-030/066",
    "name": "Trubbish",
    "supertype": "Pokémon",
    "number": "030/066",
    "rarity": "Common",
    "images": {
      "small": "https://tcgplayer-cdn.tcgplayer.com/product/600967_200w.jpg",
      "large": "https://tcgplayer-cdn.tcgplayer.com/product/600967_400w.jpg"
    },
    "tcgplayerId": "600967"
  },
  {
    "id": "jp-bw2-red-collection-040/066",
    "name": "Archeops",
    "supertype": "Pokémon",
    "number": "040/066",
    "rarity": "Uncommon",
    "images": {
      "small": "https://tcgplayer-cdn.tcgplayer.com/product/600912_200w.jpg",
      "large": "https://tcgplayer-cdn.tcgplayer.com/product/600912_400w.jpg"
    },
    "tcgplayerId": "600912"
  },
  {
    "id": "jp-bw2-red-collection-047/066",
    "name": "Landorus",
    "supertype": "Pokémon",
    "number": "047/066",
    "rarity": "Rare",
    "images": {
      "small": "https://tcgplayer-cdn.tcgplayer.com/product/600948_200w.jpg",
      "large": "https://tcgplayer-cdn.tcgplayer.com/product/600948_400w.jpg"
    },
    "tcgplayerId": "600948"
  },
  {
    "id": "jp-bw2-red-collection-036/066",
    "name": "Chandelure",
    "supertype": "Pokémon",
    "number": "036/066",
    "rarity": "Uncommon",
    "images": {
      "small": "https://tcgplayer-cdn.tcgplayer.com/product/600917_200w.jpg",
      "large": "https://tcgplayer-cdn.tcgplayer.com/product/600917_400w.jpg"
    },
    "tcgplayerId": "600917"
  },
  {
    "id": "jp-bw2-red-collection-053/066",
    "name": "Escavalier",
    "supertype": "Pokémon",
    "number": "053/066",
    "rarity": "Uncommon",
    "images": {
      "small": "https://tcgplayer-cdn.tcgplayer.com/product/600932_200w.jpg",
      "large": "https://tcgplayer-cdn.tcgplayer.com/product/600932_400w.jpg"
    },
    "tcgplayerId": "600932"
  },
  {
    "id": "jp-bw2-red-collection-033/066",
    "name": "Beheeyem",
    "supertype": "Pokémon",
    "number": "033/066",
    "rarity": "Uncommon",
    "images": {
      "small": "https://tcgplayer-cdn.tcgplayer.com/product/600914_200w.jpg",
      "large": "https://tcgplayer-cdn.tcgplayer.com/product/600914_400w.jpg"
    },
    "tcgplayerId": "600914"
  },
  {
    "id": "jp-bw2-red-collection-015/066",
    "name": "Seismitoad",
    "supertype": "Pokémon",
    "number": "015/066",
    "rarity": "Uncommon",
    "images": {
      "small": "https://tcgplayer-cdn.tcgplayer.com/product/600960_200w.jpg",
      "large": "https://tcgplayer-cdn.tcgplayer.com/product/600960_400w.jpg"
    },
    "tcgplayerId": "600960"
  },
  {
    "id": "jp-bw2-red-collection-025/066",
    "name": "Tynamo",
    "supertype": "Pokémon",
    "number": "025/066",
    "rarity": "Common",
    "images": {
      "small": "https://tcgplayer-cdn.tcgplayer.com/product/600969_200w.jpg",
      "large": "https://tcgplayer-cdn.tcgplayer.com/product/600969_400w.jpg"
    },
    "tcgplayerId": "600969"
  },
  {
    "id": "jp-bw2-red-collection-034/066",
    "name": "Litwick",
    "supertype": "Pokémon",
    "number": "034/066",
    "rarity": "Common",
    "images": {
      "small": "https://tcgplayer-cdn.tcgplayer.com/product/600950_200w.jpg",
      "large": "https://tcgplayer-cdn.tcgplayer.com/product/600950_400w.jpg"
    },
    "tcgplayerId": "600950"
  },
  {
    "id": "jp-bw2-red-collection-035/066",
    "name": "Lampent",
    "supertype": "Pokémon",
    "number": "035/066",
    "rarity": "Common",
    "images": {
      "small": "https://tcgplayer-cdn.tcgplayer.com/product/600947_200w.jpg",
      "large": "https://tcgplayer-cdn.tcgplayer.com/product/600947_400w.jpg"
    },
    "tcgplayerId": "600947"
  },
  {
    "id": "jp-bw2-red-collection-011/066",
    "name": "Larvesta",
    "supertype": "Pokémon",
    "number": "011/066",
    "rarity": "Common",
    "images": {
      "small": "https://tcgplayer-cdn.tcgplayer.com/product/600949_200w.jpg",
      "large": "https://tcgplayer-cdn.tcgplayer.com/product/600949_400w.jpg"
    },
    "tcgplayerId": "600949"
  },
  {
    "id": "jp-bw2-red-collection-057/066",
    "name": "Fraxure",
    "supertype": "Pokémon",
    "number": "057/066",
    "rarity": "Uncommon",
    "images": {
      "small": "https://tcgplayer-cdn.tcgplayer.com/product/600935_200w.jpg",
      "large": "https://tcgplayer-cdn.tcgplayer.com/product/600935_400w.jpg"
    },
    "tcgplayerId": "600935"
  },
  {
    "id": "jp-bw2-red-collection-014/066",
    "name": "Palpitoad",
    "supertype": "Pokémon",
    "number": "014/066",
    "rarity": "Common",
    "images": {
      "small": "https://tcgplayer-cdn.tcgplayer.com/product/600956_200w.jpg",
      "large": "https://tcgplayer-cdn.tcgplayer.com/product/600956_400w.jpg"
    },
    "tcgplayerId": "600956"
  },
  {
    "id": "jp-bw2-red-collection-054/066",
    "name": "Durant",
    "supertype": "Pokémon",
    "number": "054/066",
    "rarity": "Common",
    "images": {
      "small": "https://tcgplayer-cdn.tcgplayer.com/product/600927_200w.jpg",
      "large": "https://tcgplayer-cdn.tcgplayer.com/product/600927_400w.jpg"
    },
    "tcgplayerId": "600927"
  },
  {
    "id": "jp-bw2-red-collection-037/066",
    "name": "Gigalith",
    "supertype": "Pokémon",
    "number": "037/066",
    "rarity": "Uncommon",
    "images": {
      "small": "https://tcgplayer-cdn.tcgplayer.com/product/600938_200w.jpg",
      "large": "https://tcgplayer-cdn.tcgplayer.com/product/600938_400w.jpg"
    },
    "tcgplayerId": "600938"
  },
  {
    "id": "jp-bw2-red-collection-046/066",
    "name": "Terrakion - 046/066",
    "supertype": "Pokémon",
    "number": "046/066",
    "rarity": "Rare",
    "images": {
      "small": "https://tcgplayer-cdn.tcgplayer.com/product/600964_200w.jpg",
      "large": "https://tcgplayer-cdn.tcgplayer.com/product/600964_400w.jpg"
    },
    "tcgplayerId": "600964"
  },
  {
    "id": "jp-bw2-red-collection-060/066",
    "name": "Super Rod",
    "supertype": "Pokémon",
    "number": "060/066",
    "rarity": "Uncommon",
    "images": {
      "small": "https://tcgplayer-cdn.tcgplayer.com/product/600963_200w.jpg",
      "large": "https://tcgplayer-cdn.tcgplayer.com/product/600963_400w.jpg"
    },
    "tcgplayerId": "600963"
  },
  {
    "id": "jp-bw2-red-collection-004/066",
    "name": "Foongus",
    "supertype": "Pokémon",
    "number": "004/066",
    "rarity": "Common",
    "images": {
      "small": "https://tcgplayer-cdn.tcgplayer.com/product/600934_200w.jpg",
      "large": "https://tcgplayer-cdn.tcgplayer.com/product/600934_400w.jpg"
    },
    "tcgplayerId": "600934"
  },
  {
    "id": "jp-bw2-red-collection-012/066",
    "name": "Volcarona",
    "supertype": "Pokémon",
    "number": "012/066",
    "rarity": "Uncommon",
    "images": {
      "small": "https://tcgplayer-cdn.tcgplayer.com/product/600977_200w.jpg",
      "large": "https://tcgplayer-cdn.tcgplayer.com/product/600977_400w.jpg"
    },
    "tcgplayerId": "600977"
  },
  {
    "id": "jp-bw2-red-collection-002/066",
    "name": "Crustle",
    "supertype": "Pokémon",
    "number": "002/066",
    "rarity": "Common",
    "images": {
      "small": "https://tcgplayer-cdn.tcgplayer.com/product/600923_200w.jpg",
      "large": "https://tcgplayer-cdn.tcgplayer.com/product/600923_400w.jpg"
    },
    "tcgplayerId": "600923"
  },
  {
    "id": "jp-bw2-red-collection-007/066",
    "name": "Accelgor",
    "supertype": "Pokémon",
    "number": "007/066",
    "rarity": "Uncommon",
    "images": {
      "small": "https://tcgplayer-cdn.tcgplayer.com/product/600909_200w.jpg",
      "large": "https://tcgplayer-cdn.tcgplayer.com/product/600909_400w.jpg"
    },
    "tcgplayerId": "600909"
  },
  {
    "id": "jp-bw2-red-collection-031/066",
    "name": "Garbodor",
    "supertype": "Pokémon",
    "number": "031/066",
    "rarity": "Common",
    "images": {
      "small": "https://tcgplayer-cdn.tcgplayer.com/product/600937_200w.jpg",
      "large": "https://tcgplayer-cdn.tcgplayer.com/product/600937_400w.jpg"
    },
    "tcgplayerId": "600937"
  },
  {
    "id": "jp-bw2-red-collection-016/066",
    "name": "Tirtouga",
    "supertype": "Pokémon",
    "number": "016/066",
    "rarity": "Uncommon",
    "images": {
      "small": "https://tcgplayer-cdn.tcgplayer.com/product/600966_200w.jpg",
      "large": "https://tcgplayer-cdn.tcgplayer.com/product/600966_400w.jpg"
    },
    "tcgplayerId": "600966"
  },
  {
    "id": "jp-bw2-red-collection-051/066",
    "name": "Zweilous",
    "supertype": "Pokémon",
    "number": "051/066",
    "rarity": "Common",
    "images": {
      "small": "https://tcgplayer-cdn.tcgplayer.com/product/600980_200w.jpg",
      "large": "https://tcgplayer-cdn.tcgplayer.com/product/600980_400w.jpg"
    },
    "tcgplayerId": "600980"
  },
  {
    "id": "jp-bw2-red-collection-027/066",
    "name": "Eelektross",
    "supertype": "Pokémon",
    "number": "027/066",
    "rarity": "Rare",
    "images": {
      "small": "https://tcgplayer-cdn.tcgplayer.com/product/600930_200w.jpg",
      "large": "https://tcgplayer-cdn.tcgplayer.com/product/600930_400w.jpg"
    },
    "tcgplayerId": "600930"
  },
  {
    "id": "jp-bw2-red-collection-048/066",
    "name": "Pawniard",
    "supertype": "Pokémon",
    "number": "048/066",
    "rarity": "Common",
    "images": {
      "small": "https://tcgplayer-cdn.tcgplayer.com/product/600957_200w.jpg",
      "large": "https://tcgplayer-cdn.tcgplayer.com/product/600957_400w.jpg"
    },
    "tcgplayerId": "600957"
  },
  {
    "id": "jp-bw2-red-collection-019/066",
    "name": "Vanillish",
    "supertype": "Pokémon",
    "number": "019/066",
    "rarity": "Common",
    "images": {
      "small": "https://tcgplayer-cdn.tcgplayer.com/product/600970_200w.jpg",
      "large": "https://tcgplayer-cdn.tcgplayer.com/product/600970_400w.jpg"
    },
    "tcgplayerId": "600970"
  },
  {
    "id": "jp-bw2-red-collection-041/066",
    "name": "Stunfisk",
    "supertype": "Pokémon",
    "number": "041/066",
    "rarity": "Common",
    "images": {
      "small": "https://tcgplayer-cdn.tcgplayer.com/product/600962_200w.jpg",
      "large": "https://tcgplayer-cdn.tcgplayer.com/product/600962_400w.jpg"
    },
    "tcgplayerId": "600962"
  },
  {
    "id": "jp-bw2-red-collection-028/066",
    "name": "Yamask",
    "supertype": "Pokémon",
    "number": "028/066",
    "rarity": "Common",
    "images": {
      "small": "https://tcgplayer-cdn.tcgplayer.com/product/600979_200w.jpg",
      "large": "https://tcgplayer-cdn.tcgplayer.com/product/600979_400w.jpg"
    },
    "tcgplayerId": "600979"
  },
  {
    "id": "jp-bw2-red-collection-029/066",
    "name": "Cofagrigus",
    "supertype": "Pokémon",
    "number": "029/066",
    "rarity": "Uncommon",
    "images": {
      "small": "https://tcgplayer-cdn.tcgplayer.com/product/600920_200w.jpg",
      "large": "https://tcgplayer-cdn.tcgplayer.com/product/600920_400w.jpg"
    },
    "tcgplayerId": "600920"
  },
  {
    "id": "jp-bw2-red-collection-020/066",
    "name": "Vanilluxe",
    "supertype": "Pokémon",
    "number": "020/066",
    "rarity": "Uncommon",
    "images": {
      "small": "https://tcgplayer-cdn.tcgplayer.com/product/600972_200w.jpg",
      "large": "https://tcgplayer-cdn.tcgplayer.com/product/600972_400w.jpg"
    },
    "tcgplayerId": "600972"
  },
  {
    "id": "jp-bw2-red-collection-013/066",
    "name": "Tympole",
    "supertype": "Pokémon",
    "number": "013/066",
    "rarity": "Common",
    "images": {
      "small": "https://tcgplayer-cdn.tcgplayer.com/product/600968_200w.jpg",
      "large": "https://tcgplayer-cdn.tcgplayer.com/product/600968_400w.jpg"
    },
    "tcgplayerId": "600968"
  },
  {
    "id": "jp-bw2-red-collection-001/066",
    "name": "Dwebble",
    "supertype": "Pokémon",
    "number": "001/066",
    "rarity": "Common",
    "images": {
      "small": "https://tcgplayer-cdn.tcgplayer.com/product/600928_200w.jpg",
      "large": "https://tcgplayer-cdn.tcgplayer.com/product/600928_400w.jpg"
    },
    "tcgplayerId": "600928"
  },
  {
    "id": "jp-bw2-red-collection-018/066",
    "name": "Vanillite",
    "supertype": "Pokémon",
    "number": "018/066",
    "rarity": "Common",
    "images": {
      "small": "https://tcgplayer-cdn.tcgplayer.com/product/600971_200w.jpg",
      "large": "https://tcgplayer-cdn.tcgplayer.com/product/600971_400w.jpg"
    },
    "tcgplayerId": "600971"
  },
  {
    "id": "jp-bw2-red-collection-023/066",
    "name": "Cryogonal",
    "supertype": "Pokémon",
    "number": "023/066",
    "rarity": "Uncommon",
    "images": {
      "small": "https://tcgplayer-cdn.tcgplayer.com/product/600924_200w.jpg",
      "large": "https://tcgplayer-cdn.tcgplayer.com/product/600924_400w.jpg"
    },
    "tcgplayerId": "600924"
  },
  {
    "id": "jp-bw2-red-collection-042/066",
    "name": "Mienfoo",
    "supertype": "Pokémon",
    "number": "042/066",
    "rarity": "Common",
    "images": {
      "small": "https://tcgplayer-cdn.tcgplayer.com/product/600952_200w.jpg",
      "large": "https://tcgplayer-cdn.tcgplayer.com/product/600952_400w.jpg"
    },
    "tcgplayerId": "600952"
  },
  {
    "id": "jp-bw2-red-collection-021/066",
    "name": "Frillish",
    "supertype": "Pokémon",
    "number": "021/066",
    "rarity": "Common",
    "images": {
      "small": "https://tcgplayer-cdn.tcgplayer.com/product/600936_200w.jpg",
      "large": "https://tcgplayer-cdn.tcgplayer.com/product/600936_400w.jpg"
    },
    "tcgplayerId": "600936"
  },
  {
    "id": "jp-bw2-red-collection-017/066",
    "name": "Carracosta",
    "supertype": "Pokémon",
    "number": "017/066",
    "rarity": "Uncommon",
    "images": {
      "small": "https://tcgplayer-cdn.tcgplayer.com/product/600916_200w.jpg",
      "large": "https://tcgplayer-cdn.tcgplayer.com/product/600916_400w.jpg"
    },
    "tcgplayerId": "600916"
  },
  {
    "id": "jp-bw2-red-collection-038/066",
    "name": "Conkeldurr",
    "supertype": "Pokémon",
    "number": "038/066",
    "rarity": "Uncommon",
    "images": {
      "small": "https://tcgplayer-cdn.tcgplayer.com/product/600921_200w.jpg",
      "large": "https://tcgplayer-cdn.tcgplayer.com/product/600921_400w.jpg"
    },
    "tcgplayerId": "600921"
  },
  {
    "id": "jp-bw2-red-collection-043/066",
    "name": "Mienshao",
    "supertype": "Pokémon",
    "number": "043/066",
    "rarity": "Common",
    "images": {
      "small": "https://tcgplayer-cdn.tcgplayer.com/product/600953_200w.jpg",
      "large": "https://tcgplayer-cdn.tcgplayer.com/product/600953_400w.jpg"
    },
    "tcgplayerId": "600953"
  },
  {
    "id": "jp-bw2-red-collection-059/066",
    "name": "Druddigon",
    "supertype": "Pokémon",
    "number": "059/066",
    "rarity": "Uncommon",
    "images": {
      "small": "https://tcgplayer-cdn.tcgplayer.com/product/600926_200w.jpg",
      "large": "https://tcgplayer-cdn.tcgplayer.com/product/600926_400w.jpg"
    },
    "tcgplayerId": "600926"
  },
  {
    "id": "jp-bw2-red-collection-032/066",
    "name": "Elgyem",
    "supertype": "Pokémon",
    "number": "032/066",
    "rarity": "Common",
    "images": {
      "small": "https://tcgplayer-cdn.tcgplayer.com/product/600931_200w.jpg",
      "large": "https://tcgplayer-cdn.tcgplayer.com/product/600931_400w.jpg"
    },
    "tcgplayerId": "600931"
  },
  {
    "id": "jp-bw2-red-collection-003/066",
    "name": "Karrablast",
    "supertype": "Pokémon",
    "number": "003/066",
    "rarity": "Common",
    "images": {
      "small": "https://tcgplayer-cdn.tcgplayer.com/product/600945_200w.jpg",
      "large": "https://tcgplayer-cdn.tcgplayer.com/product/600945_400w.jpg"
    },
    "tcgplayerId": "600945"
  }
]