[
  {
    "id": "jp-ll-lost-link-018/040",
    "name": "Mew",
    "supertype": "Pokémon",
    "number": "018/040",
    "rarity": "Super Rare Holo",
    "images": {
      "small": "https://tcgplayer-cdn.tcgplayer.com/product/608637_200w.jpg",
      "large": "https://tcgplayer-cdn.tcgplayer.com/product/608637_400w.jpg"
    },
    "tcgplayerId": "608637"
  },
  {
    "id": "jp-ll-lost-link-035/040",
    "name": "Darkrai \u0026 Cresselia Legend - 035/040",
    "supertype": "Pokémon",
    "number": "035/040",
    "rarity": "Rare Holo LEGEND",
    "images": {
      "small": "https://tcgplayer-cdn.tcgplayer.com/product/608654_200w.jpg",
      "large": "https://tcgplayer-cdn.tcgplayer.com/product/608654_400w.jpg"
    },
    "tcgplayerId": "608654"
  },
  {
    "id": "jp-ll-lost-link-036/040",
    "name": "Darkrai \u0026 Cresselia Legend - 036/040",
    "supertype": "Pokémon",
    "number": "036/040",
    "rarity": "Rare Holo LEGEND",
    "images": {
      "small": "https://tcgplayer-cdn.tcgplayer.com/product/608655_200w.jpg",
      "large": "https://tcgplayer-cdn.tcgplayer.com/product/608655_400w.jpg"
    },
    "tcgplayerId": "608655"
  },
  {
    "id": "jp-ll-lost-link-028/040",
    "name": "Snorlax",
    "supertype": "Pokémon",
    "number": "028/040",
    "rarity": "Holo Rare",
    "images": {
      "small": "https://tcgplayer-cdn.tcgplayer.com/product/608647_200w.jpg",
      "large": "https://tcgplayer-cdn.tcgplayer.com/product/608647_400w.jpg"
    },
    "tcgplayerId": "608647"
  },
  {
    "id": "jp-ll-lost-link-033/040",
    "name": "Altaria",
    "supertype": "Pokémon",
    "number": "033/040",
    "rarity": "Holo Rare",
    "images": {
      "small": "https://tcgplayer-cdn.tcgplayer.com/product/608652_200w.jpg",
      "large": "https://tcgplayer-cdn.tcgplayer.com/product/608652_400w.jpg"
    },
    "tcgplayerId": "608652"
  },
  {
    "id": "jp-ll-lost-link-022/040",
    "name": "Spiritomb",
    "supertype": "Pokémon",
    "number": "022/040",
    "rarity": "Holo Rare",
    "images": {
      "small": "https://tcgplayer-cdn.tcgplayer.com/product/608641_200w.jpg",
      "large": "https://tcgplayer-cdn.tcgplayer.com/product/608641_400w.jpg"
    },
    "tcgplayerId": "608641"
  },
  {
    "id": "jp-ll-lost-link-031/040",
    "name": "Dragonite",
    "supertype": "Pokémon",
    "number": "031/040",
    "rarity": "Rare",
    "images": {
      "small": "https://tcgplayer-cdn.tcgplayer.com/product/608650_200w.jpg",
      "large": "https://tcgplayer-cdn.tcgplayer.com/product/608650_400w.jpg"
    },
    "tcgplayerId": "608650"
  },
  {
    "id": "jp-ll-lost-link-011/040",
    "name": "Magnezone",
    "supertype": "Pokémon",
    "number": "011/040",
    "rarity": "Super Rare Holo",
    "images": {
      "small": "https://tcgplayer-cdn.tcgplayer.com/product/608630_200w.jpg",
      "large": "https://tcgplayer-cdn.tcgplayer.com/product/608630_400w.jpg"
    },
    "tcgplayerId": "608630"
  },
  {
    "id": "jp-ll-lost-link-025/040",
    "name": "Riolu",
    "supertype": "Pokémon",
    "number": "025/040",
    "rarity": "Uncommon",
    "images": {
      "small": "https://tcgplayer-cdn.tcgplayer.com/product/608644_200w.jpg",
      "large": "https://tcgplayer-cdn.tcgplayer.com/product/608644_400w.jpg"
    },
    "tcgplayerId": "608644"
  },
  {
    "id": "jp-ll-lost-link-014/040",
    "name": "Haunter",
    "supertype": "Pokémon",
    "number": "014/040",
    "rarity": "Uncommon",
    "images": {
      "small": "https://tcgplayer-cdn.tcgplayer.com/product/608633_200w.jpg",
      "large": "https://tcgplayer-cdn.tcgplayer.com/product/608633_400w.jpg"
    },
    "tcgplayerId": "608633"
  },
  {
    "id": "jp-ll-lost-link-026/040",
    "name": "Lucario",
    "supertype": "Pokémon",
    "number": "026/040",
    "rarity": "Holo Rare",
    "images": {
      "small": "https://tcgplayer-cdn.tcgplayer.com/product/608645_200w.jpg",
      "large": "https://tcgplayer-cdn.tcgplayer.com/product/608645_400w.jpg"
    },
    "tcgplayerId": "608645"
  },
  {
    "id": "jp-ll-lost-link-012/040",
    "name": "Pachirisu",
    "supertype": "Pokémon",
    "number": "012/040",
    "rarity": "Holo Rare",
    "images": {
      "small": "https://tcgplayer-cdn.tcgplayer.com/product/608631_200w.jpg",
      "large": "https://tcgplayer-cdn.tcgplayer.com/product/608631_400w.jpg"
    },
    "tcgplayerId": "608631"
  },
  {
    "id": "jp-ll-lost-link-003/040",
    "name": "Tangela",
    "supertype": "Pokémon",
    "number": "003/040",
    "rarity": "Common",
    "images": {
      "small": "https://tcgplayer-cdn.tcgplayer.com/product/608622_200w.jpg",
      "large": "https://tcgplayer-cdn.tcgplayer.com/product/608622_400w.jpg"
    },
    "tcgplayerId": "608622"
  },
  {
    "id": "jp-ll-lost-link-039/040",
    "name": "Seeker",
    "supertype": "Pokémon",
    "number": "039/040",
    "rarity": "Uncommon",
    "images": {
      "small": "https://tcgplayer-cdn.tcgplayer.com/product/608658_200w.jpg",
      "large": "https://tcgplayer-cdn.tcgplayer.com/product/608658_400w.jpg"
    },
    "tcgplayerId": "608658"
  },
  {
    "id": "jp-ll-lost-link-013/040",
    "name": "Gastly",
    "supertype": "Pokémon",
    "number": "013/040",
    "rarity": "Common",
    "images": {
      "small": "https://tcgplayer-cdn.tcgplayer.com/product/608632_200w.jpg",
      "large": "https://tcgplayer-cdn.tcgplayer.com/product/608632_400w.jpg"
    },
    "tcgplayerId": "608632"
  },
  {
    "id": "jp-ll-lost-link-032/040",
    "name": "Swablu",
    "supertype": "Pokémon",
    "number": "032/040",
    "rarity": "Common",
    "images": {
      "small": "https://tcgplayer-cdn.tcgplayer.com/product/608651_200w.jpg",
      "large": "https://tcgplayer-cdn.tcgplayer.com/product/608651_400w.jpg"
    },
    "tcgplayerId": "608651"
  },
  {
    "id": "jp-ll-lost-link-029/040",
    "name": "Dratini",
    "supertype": "Pokémon",
    "number": "029/040",
    "rarity": "Common",
    "images": {
      "small": "https://tcgplayer-cdn.tcgplayer.com/product/608648_200w.jpg",
      "large": "https://tcgplayer-cdn.tcgplayer.com/product/608648_400w.jpg"
    },
    "tcgplayerId": "608648"
  },
  {
    "id": "jp-ll-lost-link-010/040",
    "name": "Magneton",
    "supertype": "Pokémon",
    "number": "010/040",
    "rarity": "Uncommon",
    "images": {
      "small": "https://tcgplayer-cdn.tcgplayer.com/product/608629_200w.jpg",
      "large": "https://tcgplayer-cdn.tcgplayer.com/product/608629_400w.jpg"
    },
    "tcgplayerId": "608629"
  },
  {
    "id": "jp-ll-lost-link-004/040",
    "name": "Tangrowth",
    "supertype": "Pokémon",
    "number": "004/040",
    "rarity": "Uncommon",
    "images": {
      "small": "https://tcgplayer-cdn.tcgplayer.com/product/608623_200w.jpg",
      "large": "https://tcgplayer-cdn.tcgplayer.com/product/608623_400w.jpg"
    },
    "tcgplayerId": "608623"
  },
  {
    "id": "jp-ll-lost-link-030/040",
    "name": "Dragonair",
    "supertype": "Pokémon",
    "number": "030/040",
    "rarity": "Common",
    "images": {
      "small": "https://tcgplayer-cdn.tcgplayer.com/product/608649_200w.jpg",
      "large": "https://tcgplayer-cdn.tcgplayer.com/product/608649_400w.jpg"
    },
    "tcgplayerId": "608649"
  }
]