[
  {
    "id": "jp-s5a-peerless-fighters-078/070",
    "name": "Galarian Moltres V - 078/070",
    "supertype": "Pokémon",
    "number": "078/070",
    "rarity": "Super Rare",
    "images": {
      "small": "https://tcgplayer-cdn.tcgplayer.com/product/570443_200w.jpg",
      "large": "https://tcgplayer-cdn.tcgplayer.com/product/570443_400w.jpg"
    },
    "tcgplayerId": "570443"
  },
  {
    "id": "jp-s5a-peerless-fighters-peerless-fighters-master-booster-box",
    "name": "Peerless Fighters Master Booster Box",
    "supertype": "Pokémon",
    "number": "N/A",
    "rarity": "None",
    "images": {
      "small": "https://tcgplayer-cdn.tcgplayer.com/product/565362_200w.jpg",
      "large": "https://tcgplayer-cdn.tcgplayer.com/product/565362_400w.jpg"
    },
    "tcgplayerId": "565362"
  },
  {
    "id": "jp-s5a-peerless-fighters-093/070",
    "name": "Snorlax",
    "supertype": "Pokémon",
    "number": "093/070",
    "rarity": "Ultra Rare",
    "images": {
      "small": "https://tcgplayer-cdn.tcgplayer.com/product/570458_200w.jpg",
      "large": "https://tcgplayer-cdn.tcgplayer.com/product/570458_400w.jpg"
    },
    "tcgplayerId": "570458"
  },
  {
    "id": "jp-s5a-peerless-fighters-080/070",
    "name": "Galarian Slowking V - 080/070",
    "supertype": "Pokémon",
    "number": "080/070",
    "rarity": "Super Rare",
    "images": {
      "small": "https://tcgplayer-cdn.tcgplayer.com/product/570445_200w.jpg",
      "large": "https://tcgplayer-cdn.tcgplayer.com/product/570445_400w.jpg"
    },
    "tcgplayerId": "570445"
  },
  {
    "id": "jp-s5a-peerless-fighters-074/070",
    "name": "Galarian Articuno V - 074/070",
    "supertype": "Pokémon",
    "number": "074/070",
    "rarity": "Super Rare",
    "images": {
      "small": "https://tcgplayer-cdn.tcgplayer.com/product/570439_200w.jpg",
      "large": "https://tcgplayer-cdn.tcgplayer.com/product/570439_400w.jpg"
    },
    "tcgplayerId": "570439"
  },
  {
    "id": "jp-s5a-peerless-fighters-076/070",
    "name": "Galarian Zapdos V - 076/070",
    "supertype": "Pokémon",
    "number": "076/070",
    "rarity": "Super Rare",
    "images": {
      "small": "https://tcgplayer-cdn.tcgplayer.com/product/570441_200w.jpg",
      "large": "https://tcgplayer-cdn.tcgplayer.com/product/570441_400w.jpg"
    },
    "tcgplayerId": "570441"
  },
  {
    "id": "jp-s5a-peerless-fighters-082/070",
    "name": "Klara - 082/070",
    "supertype": "Pokémon",
    "number": "082/070",
    "rarity": "Super Rare",
    "images": {
      "small": "https://tcgplayer-cdn.tcgplayer.com/product/570447_200w.jpg",
      "large": "https://tcgplayer-cdn.tcgplayer.com/product/570447_400w.jpg"
    },
    "tcgplayerId": "570447"
  },
  {
    "id": "jp-s5a-peerless-fighters-085/070",
    "name": "Blaziken VMAX - 085/070",
    "supertype": "Pokémon",
    "number": "085/070",
    "rarity": "Hyper Rare",
    "images": {
      "small": "https://tcgplayer-cdn.tcgplayer.com/product/570450_200w.jpg",
      "large": "https://tcgplayer-cdn.tcgplayer.com/product/570450_400w.jpg"
    },
    "tcgplayerId": "570450"
  },
  {
    "id": "jp-s5a-peerless-fighters-096/070",
    "name": "Basic Fighting Energy",
    "supertype": "Energy",
    "number": "096/070",
    "rarity": "Ultra Rare",
    "images": {
      "small": "https://tcgplayer-cdn.tcgplayer.com/product/570461_200w.jpg",
      "large": "https://tcgplayer-cdn.tcgplayer.com/product/570461_400w.jpg"
    },
    "tcgplayerId": "570461"
  },
  {
    "id": "jp-s5a-peerless-fighters-081/070",
    "name": "Karen's Conviction - 081/070",
    "supertype": "Pokémon",
    "number": "081/070",
    "rarity": "Super Rare",
    "images": {
      "small": "https://tcgplayer-cdn.tcgplayer.com/product/570446_200w.jpg",
      "large": "https://tcgplayer-cdn.tcgplayer.com/product/570446_400w.jpg"
    },
    "tcgplayerId": "570446"
  },
  {
    "id": "jp-s5a-peerless-fighters-089/070",
    "name": "Karen's Conviction - 089/070",
    "supertype": "Pokémon",
    "number": "089/070",
    "rarity": "Hyper Rare",
    "images": {
      "small": "https://tcgplayer-cdn.tcgplayer.com/product/570454_200w.jpg",
      "large": "https://tcgplayer-cdn.tcgplayer.com/product/570454_400w.jpg"
    },
    "tcgplayerId": "570454"
  },
  {
    "id": "jp-s5a-peerless-fighters-077/070",
    "name": "Galarian Moltres V - 077/070",
    "supertype": "Pokémon",
    "number": "077/070",
    "rarity": "Super Rare",
    "images": {
      "small": "https://tcgplayer-cdn.tcgplayer.com/product/570442_200w.jpg",
      "large": "https://tcgplayer-cdn.tcgplayer.com/product/570442_400w.jpg"
    },
    "tcgplayerId": "570442"
  },
  {
    "id": "jp-s5a-peerless-fighters-088/070",
    "name": "Galarian Slowking VMAX - 088/070",
    "supertype": "Pokémon",
    "number": "088/070",
    "rarity": "Hyper Rare",
    "images": {
      "small": "https://tcgplayer-cdn.tcgplayer.com/product/570453_200w.jpg",
      "large": "https://tcgplayer-cdn.tcgplayer.com/product/570453_400w.jpg"
    },
    "tcgplayerId": "570453"
  },
  {
    "id": "jp-s5a-peerless-fighters-087/070",
    "name": "Dracozolt VMAX - 087/070",
    "supertype": "Pokémon",
    "number": "087/070",
    "rarity": "Hyper Rare",
    "images": {
      "small": "https://tcgplayer-cdn.tcgplayer.com/product/570452_200w.jpg",
      "large": "https://tcgplayer-cdn.tcgplayer.com/product/570452_400w.jpg"
    },
    "tcgplayerId": "570452"
  },
  {
    "id": "jp-s5a-peerless-fighters-peerless-fighters-master-booster-pack",
    "name": "Peerless Fighters Master Booster Pack",
    "supertype": "Pokémon",
    "number": "N/A",
    "rarity": "None",
    "images": {
      "small": "https://tcgplayer-cdn.tcgplayer.com/product/565363_200w.jpg",
      "large": "https://tcgplayer-cdn.tcgplayer.com/product/565363_400w.jpg"
    },
    "tcgplayerId": "565363"
  },
  {
    "id": "jp-s5a-peerless-fighters-073/070",
    "name": "Galarian Articuno V - 073/070",
    "supertype": "Pokémon",
    "number": "073/070",
    "rarity": "Super Rare",
    "images": {
      "small": "https://tcgplayer-cdn.tcgplayer.com/product/570438_200w.jpg",
      "large": "https://tcgplayer-cdn.tcgplayer.com/product/570438_400w.jpg"
    },
    "tcgplayerId": "570438"
  },
  {
    "id": "jp-s5a-peerless-fighters-091/070",
    "name": "Avery - 091/070",
    "supertype": "Pokémon",
    "number": "091/070",
    "rarity": "Hyper Rare",
    "images": {
      "small": "https://tcgplayer-cdn.tcgplayer.com/product/570456_200w.jpg",
      "large": "https://tcgplayer-cdn.tcgplayer.com/product/570456_400w.jpg"
    },
    "tcgplayerId": "570456"
  },
  {
    "id": "jp-s5a-peerless-fighters-071/070",
    "name": "Blaziken V - 071/070",
    "supertype": "Pokémon",
    "number": "071/070",
    "rarity": "Super Rare",
    "images": {
      "small": "https://tcgplayer-cdn.tcgplayer.com/product/570436_200w.jpg",
      "large": "https://tcgplayer-cdn.tcgplayer.com/product/570436_400w.jpg"
    },
    "tcgplayerId": "570436"
  },
  {
    "id": "jp-s5a-peerless-fighters-075/070",
    "name": "Galarian Zapdos V - 075/070",
    "supertype": "Pokémon",
    "number": "075/070",
    "rarity": "Super Rare",
    "images": {
      "small": "https://tcgplayer-cdn.tcgplayer.com/product/570440_200w.jpg",
      "large": "https://tcgplayer-cdn.tcgplayer.com/product/570440_400w.jpg"
    },
    "tcgplayerId": "570440"
  },
  {
    "id": "jp-s5a-peerless-fighters-083/070",
    "name": "Avery - 083/070",
    "supertype": "Pokémon",
    "number": "083/070",
    "rarity": "Super Rare",
    "images": {
      "small": "https://tcgplayer-cdn.tcgplayer.com/product/570448_200w.jpg",
      "large": "https://tcgplayer-cdn.tcgplayer.com/product/570448_400w.jpg"
    },
    "tcgplayerId": "570448"
  },
  {
    "id": "jp-s5a-peerless-fighters-079/070",
    "name": "Galarian Slowking V - 079/070",
    "supertype": "Pokémon",
    "number": "079/070",
    "rarity": "Super Rare",
    "images": {
      "small": "https://tcgplayer-cdn.tcgplayer.com/product/570444_200w.jpg",
      "large": "https://tcgplayer-cdn.tcgplayer.com/product/570444_400w.jpg"
    },
    "tcgplayerId": "570444"
  },
  {
    "id": "jp-s5a-peerless-fighters-092/070",
    "name": "Brawly - 092/070",
    "supertype": "Pokémon",
    "number": "092/070",
    "rarity": "Hyper Rare",
    "images": {
      "small": "https://tcgplayer-cdn.tcgplayer.com/product/570457_200w.jpg",
      "large": "https://tcgplayer-cdn.tcgplayer.com/product/570457_400w.jpg"
    },
    "tcgplayerId": "570457"
  },
  {
    "id": "jp-s5a-peerless-fighters-084/070",
    "name": "Brawly - 084/070",
    "supertype": "Pokémon",
    "number": "084/070",
    "rarity": "Super Rare",
    "images": {
      "small": "https://tcgplayer-cdn.tcgplayer.com/product/570449_200w.jpg",
      "large": "https://tcgplayer-cdn.tcgplayer.com/product/570449_400w.jpg"
    },
    "tcgplayerId": "570449"
  },
  {
    "id": "jp-s5a-peerless-fighters-072/070",
    "name": "Dracozolt V - 072/070",
    "supertype": "Pokémon",
    "number": "072/070",
    "rarity": "Super Rare",
    "images": {
      "small": "https://tcgplayer-cdn.tcgplayer.com/product/570437_200w.jpg",
      "large": "https://tcgplayer-cdn.tcgplayer.com/product/570437_400w.jpg"
    },
    "tcgplayerId": "570437"
  },
  {
    "id": "jp-s5a-peerless-fighters-008/070",
    "name": "Blaziken VMAX - 008/070",
    "supertype": "Pokémon",
    "number": "008/070",
    "rarity": "Triple Rare",
    "images": {
      "small": "https://tcgplayer-cdn.tcgplayer.com/product/570373_200w.jpg",
      "large": "https://tcgplayer-cdn.tcgplayer.com/product/570373_400w.jpg"
    },
    "tcgplayerId": "570373"
  },
  {
    "id": "jp-s5a-peerless-fighters-007/070",
    "name": "Blaziken V - 007/070",
    "supertype": "Pokémon",
    "number": "007/070",
    "rarity": "Double Rare",
    "images": {
      "small": "https://tcgplayer-cdn.tcgplayer.com/product/570372_200w.jpg",
      "large": "https://tcgplayer-cdn.tcgplayer.com/product/570372_400w.jpg"
    },
    "tcgplayerId": "570372"
  },
  {
    "id": "jp-s5a-peerless-fighters-024/070",
    "name": "Dracozolt VMAX - 024/070",
    "supertype": "Pokémon",
    "number": "024/070",
    "rarity": "Triple Rare",
    "images": {
      "small": "https://tcgplayer-cdn.tcgplayer.com/product/570389_200w.jpg",
      "large": "https://tcgplayer-cdn.tcgplayer.com/product/570389_400w.jpg"
    },
    "tcgplayerId": "570389"
  },
  {
    "id": "jp-s5a-peerless-fighters-047/070",
    "name": "Galarian Slowking VMAX - 047/070",
    "supertype": "Pokémon",
    "number": "047/070",
    "rarity": "Triple Rare",
    "images": {
      "small": "https://tcgplayer-cdn.tcgplayer.com/product/570412_200w.jpg",
      "large": "https://tcgplayer-cdn.tcgplayer.com/product/570412_400w.jpg"
    },
    "tcgplayerId": "570412"
  },
  {
    "id": "jp-s5a-peerless-fighters-025/070",
    "name": "Galarian Articuno V - 025/070",
    "supertype": "Pokémon",
    "number": "025/070",
    "rarity": "Double Rare",
    "images": {
      "small": "https://tcgplayer-cdn.tcgplayer.com/product/570390_200w.jpg",
      "large": "https://tcgplayer-cdn.tcgplayer.com/product/570390_400w.jpg"
    },
    "tcgplayerId": "570390"
  },
  {
    "id": "jp-s5a-peerless-fighters-045/070",
    "name": "Galarian Moltres V - 045/070",
    "supertype": "Pokémon",
    "number": "045/070",
    "rarity": "Double Rare",
    "images": {
      "small": "https://tcgplayer-cdn.tcgplayer.com/product/570410_200w.jpg",
      "large": "https://tcgplayer-cdn.tcgplayer.com/product/570410_400w.jpg"
    },
    "tcgplayerId": "570410"
  },
  {
    "id": "jp-s5a-peerless-fighters-037/070",
    "name": "Galarian Zapdos V - 037/070",
    "supertype": "Pokémon",
    "number": "037/070",
    "rarity": "Double Rare",
    "images": {
      "small": "https://tcgplayer-cdn.tcgplayer.com/product/570402_200w.jpg",
      "large": "https://tcgplayer-cdn.tcgplayer.com/product/570402_400w.jpg"
    },
    "tcgplayerId": "570402"
  },
  {
    "id": "jp-s5a-peerless-fighters-046/070",
    "name": "Galarian Slowking V - 046/070",
    "supertype": "Pokémon",
    "number": "046/070",
    "rarity": "Double Rare",
    "images": {
      "small": "https://tcgplayer-cdn.tcgplayer.com/product/570411_200w.jpg",
      "large": "https://tcgplayer-cdn.tcgplayer.com/product/570411_400w.jpg"
    },
    "tcgplayerId": "570411"
  },
  {
    "id": "jp-s5a-peerless-fighters-004/070",
    "name": "Heracross",
    "supertype": "Pokémon",
    "number": "004/070",
    "rarity": "Common",
    "images": {
      "small": "https://tcgplayer-cdn.tcgplayer.com/product/570369_200w.jpg",
      "large": "https://tcgplayer-cdn.tcgplayer.com/product/570369_400w.jpg"
    },
    "tcgplayerId": "570369"
  },
  {
    "id": "jp-s5a-peerless-fighters-023/070",
    "name": "Dracozolt V - 023/070",
    "supertype": "Pokémon",
    "number": "023/070",
    "rarity": "Double Rare",
    "images": {
      "small": "https://tcgplayer-cdn.tcgplayer.com/product/570388_200w.jpg",
      "large": "https://tcgplayer-cdn.tcgplayer.com/product/570388_400w.jpg"
    },
    "tcgplayerId": "570388"
  },
  {
    "id": "jp-s5a-peerless-fighters-057/070",
    "name": "Shaymin",
    "supertype": "Pokémon",
    "number": "057/070",
    "rarity": "Rare",
    "images": {
      "small": "https://tcgplayer-cdn.tcgplayer.com/product/570422_200w.jpg",
      "large": "https://tcgplayer-cdn.tcgplayer.com/product/570422_400w.jpg"
    },
    "tcgplayerId": "570422"
  },
  {
    "id": "jp-s5a-peerless-fighters-003/070",
    "name": "Beedrill",
    "supertype": "Pokémon",
    "number": "003/070",
    "rarity": "Rare",
    "images": {
      "small": "https://tcgplayer-cdn.tcgplayer.com/product/570368_200w.jpg",
      "large": "https://tcgplayer-cdn.tcgplayer.com/product/570368_400w.jpg"
    },
    "tcgplayerId": "570368"
  },
  {
    "id": "jp-s5a-peerless-fighters-054/070",
    "name": "Scrafty",
    "supertype": "Pokémon",
    "number": "054/070",
    "rarity": "Uncommon",
    "images": {
      "small": "https://tcgplayer-cdn.tcgplayer.com/product/570419_200w.jpg",
      "large": "https://tcgplayer-cdn.tcgplayer.com/product/570419_400w.jpg"
    },
    "tcgplayerId": "570419"
  },
  {
    "id": "jp-s5a-peerless-fighters-032/070",
    "name": "Hatterene",
    "supertype": "Pokémon",
    "number": "032/070",
    "rarity": "Rare",
    "images": {
      "small": "https://tcgplayer-cdn.tcgplayer.com/product/570397_200w.jpg",
      "large": "https://tcgplayer-cdn.tcgplayer.com/product/570397_400w.jpg"
    },
    "tcgplayerId": "570397"
  },
  {
    "id": "jp-s5a-peerless-fighters-042/070",
    "name": "Galarian Runerigus",
    "supertype": "Pokémon",
    "number": "042/070",
    "rarity": "Rare",
    "images": {
      "small": "https://tcgplayer-cdn.tcgplayer.com/product/570407_200w.jpg",
      "large": "https://tcgplayer-cdn.tcgplayer.com/product/570407_400w.jpg"
    },
    "tcgplayerId": "570407"
  },
  {
    "id": "jp-s5a-peerless-fighters-055/070",
    "name": "Single Strike Urshifu",
    "supertype": "Pokémon",
    "number": "055/070",
    "rarity": "Rare",
    "images": {
      "small": "https://tcgplayer-cdn.tcgplayer.com/product/570420_200w.jpg",
      "large": "https://tcgplayer-cdn.tcgplayer.com/product/570420_400w.jpg"
    },
    "tcgplayerId": "570420"
  },
  {
    "id": "jp-s5a-peerless-fighters-010/070",
    "name": "Volcarona",
    "supertype": "Pokémon",
    "number": "010/070",
    "rarity": "Common",
    "images": {
      "small": "https://tcgplayer-cdn.tcgplayer.com/product/570375_200w.jpg",
      "large": "https://tcgplayer-cdn.tcgplayer.com/product/570375_400w.jpg"
    },
    "tcgplayerId": "570375"
  },
  {
    "id": "jp-s5a-peerless-fighters-048/070",
    "name": "Seviper",
    "supertype": "Pokémon",
    "number": "048/070",
    "rarity": "Common",
    "images": {
      "small": "https://tcgplayer-cdn.tcgplayer.com/product/570413_200w.jpg",
      "large": "https://tcgplayer-cdn.tcgplayer.com/product/570413_400w.jpg"
    },
    "tcgplayerId": "570413"
  },
  {
    "id": "jp-s5a-peerless-fighters-069/070",
    "name": "Brawly - 069/070",
    "supertype": "Pokémon",
    "number": "069/070",
    "rarity": "Uncommon",
    "images": {
      "small": "https://tcgplayer-cdn.tcgplayer.com/product/570434_200w.jpg",
      "large": "https://tcgplayer-cdn.tcgplayer.com/product/570434_400w.jpg"
    },
    "tcgplayerId": "570434"
  },
  {
    "id": "jp-s5a-peerless-fighters-029/070",
    "name": "Slurpuff",
    "supertype": "Pokémon",
    "number": "029/070",
    "rarity": "Uncommon",
    "images": {
      "small": "https://tcgplayer-cdn.tcgplayer.com/product/570394_200w.jpg",
      "large": "https://tcgplayer-cdn.tcgplayer.com/product/570394_400w.jpg"
    },
    "tcgplayerId": "570394"
  },
  {
    "id": "jp-s5a-peerless-fighters-026/070",
    "name": "Woobat",
    "supertype": "Pokémon",
    "number": "026/070",
    "rarity": "Common",
    "images": {
      "small": "https://tcgplayer-cdn.tcgplayer.com/product/570391_200w.jpg",
      "large": "https://tcgplayer-cdn.tcgplayer.com/product/570391_400w.jpg"
    },
    "tcgplayerId": "570391"
  },
  {
    "id": "jp-s5a-peerless-fighters-044/070",
    "name": "Kubfu",
    "supertype": "Pokémon",
    "number": "044/070",
    "rarity": "Common",
    "images": {
      "small": "https://tcgplayer-cdn.tcgplayer.com/product/570409_200w.jpg",
      "large": "https://tcgplayer-cdn.tcgplayer.com/product/570409_400w.jpg"
    },
    "tcgplayerId": "570409"
  },
  {
    "id": "jp-s5a-peerless-fighters-031/070",
    "name": "Hattrem",
    "supertype": "Pokémon",
    "number": "031/070",
    "rarity": "Uncommon",
    "images": {
      "small": "https://tcgplayer-cdn.tcgplayer.com/product/570396_200w.jpg",
      "large": "https://tcgplayer-cdn.tcgplayer.com/product/570396_400w.jpg"
    },
    "tcgplayerId": "570396"
  },
  {
    "id": "jp-s5a-peerless-fighters-027/070",
    "name": "Swoobat",
    "supertype": "Pokémon",
    "number": "027/070",
    "rarity": "Uncommon",
    "images": {
      "small": "https://tcgplayer-cdn.tcgplayer.com/product/570392_200w.jpg",
      "large": "https://tcgplayer-cdn.tcgplayer.com/product/570392_400w.jpg"
    },
    "tcgplayerId": "570392"
  },
  {
    "id": "jp-s5a-peerless-fighters-022/070",
    "name": "Thundurus",
    "supertype": "Pokémon",
    "number": "022/070",
    "rarity": "Rare",
    "images": {
      "small": "https://tcgplayer-cdn.tcgplayer.com/product/570387_200w.jpg",
      "large": "https://tcgplayer-cdn.tcgplayer.com/product/570387_400w.jpg"
    },
    "tcgplayerId": "570387"
  },
  {
    "id": "jp-s5a-peerless-fighters-018/070",
    "name": "Inteleon",
    "supertype": "Pokémon",
    "number": "018/070",
    "rarity": "Rare",
    "images": {
      "small": "https://tcgplayer-cdn.tcgplayer.com/product/570383_200w.jpg",
      "large": "https://tcgplayer-cdn.tcgplayer.com/product/570383_400w.jpg"
    },
    "tcgplayerId": "570383"
  },
  {
    "id": "jp-s5a-peerless-fighters-001/070",
    "name": "Weedle",
    "supertype": "Pokémon",
    "number": "001/070",
    "rarity": "Common",
    "images": {
      "small": "https://tcgplayer-cdn.tcgplayer.com/product/570366_200w.jpg",
      "large": "https://tcgplayer-cdn.tcgplayer.com/product/570366_400w.jpg"
    },
    "tcgplayerId": "570366"
  },
  {
    "id": "jp-s5a-peerless-fighters-038/070",
    "name": "Roggenrola",
    "supertype": "Pokémon",
    "number": "038/070",
    "rarity": "Common",
    "images": {
      "small": "https://tcgplayer-cdn.tcgplayer.com/product/570403_200w.jpg",
      "large": "https://tcgplayer-cdn.tcgplayer.com/product/570403_400w.jpg"
    },
    "tcgplayerId": "570403"
  },
  {
    "id": "jp-s5a-peerless-fighters-019/070",
    "name": "Rapid Strike Urshifu",
    "supertype": "Pokémon",
    "number": "019/070",
    "rarity": "Rare",
    "images": {
      "small": "https://tcgplayer-cdn.tcgplayer.com/product/570384_200w.jpg",
      "large": "https://tcgplayer-cdn.tcgplayer.com/product/570384_400w.jpg"
    },
    "tcgplayerId": "570384"
  },
  {
    "id": "jp-s5a-peerless-fighters-060/070",
    "name": "Stoutland",
    "supertype": "Pokémon",
    "number": "060/070",
    "rarity": "Uncommon",
    "images": {
      "small": "https://tcgplayer-cdn.tcgplayer.com/product/570425_200w.jpg",
      "large": "https://tcgplayer-cdn.tcgplayer.com/product/570425_400w.jpg"
    },
    "tcgplayerId": "570425"
  },
  {
    "id": "jp-s5a-peerless-fighters-011/070",
    "name": "Tentacool",
    "supertype": "Pokémon",
    "number": "011/070",
    "rarity": "Common",
    "images": {
      "small": "https://tcgplayer-cdn.tcgplayer.com/product/570376_200w.jpg",
      "large": "https://tcgplayer-cdn.tcgplayer.com/product/570376_400w.jpg"
    },
    "tcgplayerId": "570376"
  },
  {
    "id": "jp-s5a-peerless-fighters-015/070",
    "name": "Sharpedo",
    "supertype": "Pokémon",
    "number": "015/070",
    "rarity": "Uncommon",
    "images": {
      "small": "https://tcgplayer-cdn.tcgplayer.com/product/570380_200w.jpg",
      "large": "https://tcgplayer-cdn.tcgplayer.com/product/570380_400w.jpg"
    },
    "tcgplayerId": "570380"
  },
  {
    "id": "jp-s5a-peerless-fighters-043/070",
    "name": "Passimian",
    "supertype": "Pokémon",
    "number": "043/070",
    "rarity": "Common",
    "images": {
      "small": "https://tcgplayer-cdn.tcgplayer.com/product/570408_200w.jpg",
      "large": "https://tcgplayer-cdn.tcgplayer.com/product/570408_400w.jpg"
    },
    "tcgplayerId": "570408"
  },
  {
    "id": "jp-s5a-peerless-fighters-036/070",
    "name": "Galarian Sirfetch'd",
    "supertype": "Pokémon",
    "number": "036/070",
    "rarity": "Uncommon",
    "images": {
      "small": "https://tcgplayer-cdn.tcgplayer.com/product/570401_200w.jpg",
      "large": "https://tcgplayer-cdn.tcgplayer.com/product/570401_400w.jpg"
    },
    "tcgplayerId": "570401"
  },
  {
    "id": "jp-s5a-peerless-fighters-017/070",
    "name": "Drizzile",
    "supertype": "Pokémon",
    "number": "017/070",
    "rarity": "Uncommon",
    "images": {
      "small": "https://tcgplayer-cdn.tcgplayer.com/product/570382_200w.jpg",
      "large": "https://tcgplayer-cdn.tcgplayer.com/product/570382_400w.jpg"
    },
    "tcgplayerId": "570382"
  },
  {
    "id": "jp-s5a-peerless-fighters-028/070",
    "name": "Swirlix",
    "supertype": "Pokémon",
    "number": "028/070",
    "rarity": "Common",
    "images": {
      "small": "https://tcgplayer-cdn.tcgplayer.com/product/570393_200w.jpg",
      "large": "https://tcgplayer-cdn.tcgplayer.com/product/570393_400w.jpg"
    },
    "tcgplayerId": "570393"
  },
  {
    "id": "jp-s5a-peerless-fighters-020/070",
    "name": "Chinchou",
    "supertype": "Pokémon",
    "number": "020/070",
    "rarity": "Common",
    "images": {
      "small": "https://tcgplayer-cdn.tcgplayer.com/product/570385_200w.jpg",
      "large": "https://tcgplayer-cdn.tcgplayer.com/product/570385_400w.jpg"
    },
    "tcgplayerId": "570385"
  },
  {
    "id": "jp-s5a-peerless-fighters-021/070",
    "name": "Lanturn",
    "supertype": "Pokémon",
    "number": "021/070",
    "rarity": "Common",
    "images": {
      "small": "https://tcgplayer-cdn.tcgplayer.com/product/570386_200w.jpg",
      "large": "https://tcgplayer-cdn.tcgplayer.com/product/570386_400w.jpg"
    },
    "tcgplayerId": "570386"
  },
  {
    "id": "jp-s5a-peerless-fighters-035/070",
    "name": "Galarian Farfetch'd",
    "supertype": "Pokémon",
    "number": "035/070",
    "rarity": "Common",
    "images": {
      "small": "https://tcgplayer-cdn.tcgplayer.com/product/570400_200w.jpg",
      "large": "https://tcgplayer-cdn.tcgplayer.com/product/570400_400w.jpg"
    },
    "tcgplayerId": "570400"
  },
  {
    "id": "jp-s5a-peerless-fighters-012/070",
    "name": "Tentacruel",
    "supertype": "Pokémon",
    "number": "012/070",
    "rarity": "Uncommon",
    "images": {
      "small": "https://tcgplayer-cdn.tcgplayer.com/product/570377_200w.jpg",
      "large": "https://tcgplayer-cdn.tcgplayer.com/product/570377_400w.jpg"
    },
    "tcgplayerId": "570377"
  },
  {
    "id": "jp-s5a-peerless-fighters-002/070",
    "name": "Kakuna",
    "supertype": "Pokémon",
    "number": "002/070",
    "rarity": "Uncommon",
    "images": {
      "small": "https://tcgplayer-cdn.tcgplayer.com/product/570367_200w.jpg",
      "large": "https://tcgplayer-cdn.tcgplayer.com/product/570367_400w.jpg"
    },
    "tcgplayerId": "570367"
  },
  {
    "id": "jp-s5a-peerless-fighters-056/070",
    "name": "Zangoose",
    "supertype": "Pokémon",
    "number": "056/070",
    "rarity": "Common",
    "images": {
      "small": "https://tcgplayer-cdn.tcgplayer.com/product/570421_200w.jpg",
      "large": "https://tcgplayer-cdn.tcgplayer.com/product/570421_400w.jpg"
    },
    "tcgplayerId": "570421"
  },
  {
    "id": "jp-s5a-peerless-fighters-006/070",
    "name": "Lilligant",
    "supertype": "Pokémon",
    "number": "006/070",
    "rarity": "Uncommon",
    "images": {
      "small": "https://tcgplayer-cdn.tcgplayer.com/product/570371_200w.jpg",
      "large": "https://tcgplayer-cdn.tcgplayer.com/product/570371_400w.jpg"
    },
    "tcgplayerId": "570371"
  },
  {
    "id": "jp-s5a-peerless-fighters-053/070",
    "name": "Scraggy",
    "supertype": "Pokémon",
    "number": "053/070",
    "rarity": "Common",
    "images": {
      "small": "https://tcgplayer-cdn.tcgplayer.com/product/570418_200w.jpg",
      "large": "https://tcgplayer-cdn.tcgplayer.com/product/570418_400w.jpg"
    },
    "tcgplayerId": "570418"
  },
  {
    "id": "jp-s5a-peerless-fighters-016/070",
    "name": "Sobble",
    "supertype": "Pokémon",
    "number": "016/070",
    "rarity": "Common",
    "images": {
      "small": "https://tcgplayer-cdn.tcgplayer.com/product/570381_200w.jpg",
      "large": "https://tcgplayer-cdn.tcgplayer.com/product/570381_400w.jpg"
    },
    "tcgplayerId": "570381"
  },
  {
    "id": "jp-s5a-peerless-fighters-068/070",
    "name": "Avery - 068/070",
    "supertype": "Pokémon",
    "number": "068/070",
    "rarity": "Uncommon",
    "images": {
      "small": "https://tcgplayer-cdn.tcgplayer.com/product/570433_200w.jpg",
      "large": "https://tcgplayer-cdn.tcgplayer.com/product/570433_400w.jpg"
    },
    "tcgplayerId": "570433"
  },
  {
    "id": "jp-s5a-peerless-fighters-013/070",
    "name": "Delibird",
    "supertype": "Pokémon",
    "number": "013/070",
    "rarity": "Common",
    "images": {
      "small": "https://tcgplayer-cdn.tcgplayer.com/product/570378_200w.jpg",
      "large": "https://tcgplayer-cdn.tcgplayer.com/product/570378_400w.jpg"
    },
    "tcgplayerId": "570378"
  },
  {
    "id": "jp-s5a-peerless-fighters-014/070",
    "name": "Carvanha",
    "supertype": "Pokémon",
    "number": "014/070",
    "rarity": "Common",
    "images": {
      "small": "https://tcgplayer-cdn.tcgplayer.com/product/570379_200w.jpg",
      "large": "https://tcgplayer-cdn.tcgplayer.com/product/570379_400w.jpg"
    },
    "tcgplayerId": "570379"
  },
  {
    "id": "jp-s5a-peerless-fighters-034/070",
    "name": "Dugtrio",
    "supertype": "Pokémon",
    "number": "034/070",
    "rarity": "Uncommon",
    "images": {
      "small": "https://tcgplayer-cdn.tcgplayer.com/product/570399_200w.jpg",
      "large": "https://tcgplayer-cdn.tcgplayer.com/product/570399_400w.jpg"
    },
    "tcgplayerId": "570399"
  },
  {
    "id": "jp-s5a-peerless-fighters-005/070",
    "name": "Petilil",
    "supertype": "Pokémon",
    "number": "005/070",
    "rarity": "Common",
    "images": {
      "small": "https://tcgplayer-cdn.tcgplayer.com/product/570370_200w.jpg",
      "large": "https://tcgplayer-cdn.tcgplayer.com/product/570370_400w.jpg"
    },
    "tcgplayerId": "570370"
  },
  {
    "id": "jp-s5a-peerless-fighters-065/070",
    "name": "Galarian Chestplate",
    "supertype": "Pokémon",
    "number": "065/070",
    "rarity": "Uncommon",
    "images": {
      "small": "https://tcgplayer-cdn.tcgplayer.com/product/570430_200w.jpg",
      "large": "https://tcgplayer-cdn.tcgplayer.com/product/570430_400w.jpg"
    },
    "tcgplayerId": "570430"
  },
  {
    "id": "jp-s5a-peerless-fighters-064/070",
    "name": "Echoing Horn",
    "supertype": "Pokémon",
    "number": "064/070",
    "rarity": "Uncommon",
    "images": {
      "small": "https://tcgplayer-cdn.tcgplayer.com/product/570429_200w.jpg",
      "large": "https://tcgplayer-cdn.tcgplayer.com/product/570429_400w.jpg"
    },
    "tcgplayerId": "570429"
  },
  {
    "id": "jp-s5a-peerless-fighters-052/070",
    "name": "Scolipede",
    "supertype": "Pokémon",
    "number": "052/070",
    "rarity": "Uncommon",
    "images": {
      "small": "https://tcgplayer-cdn.tcgplayer.com/product/570417_200w.jpg",
      "large": "https://tcgplayer-cdn.tcgplayer.com/product/570417_400w.jpg"
    },
    "tcgplayerId": "570417"
  },
  {
    "id": "jp-s5a-peerless-fighters-040/070",
    "name": "Gigalith",
    "supertype": "Pokémon",
    "number": "040/070",
    "rarity": "Uncommon",
    "images": {
      "small": "https://tcgplayer-cdn.tcgplayer.com/product/570405_200w.jpg",
      "large": "https://tcgplayer-cdn.tcgplayer.com/product/570405_400w.jpg"
    },
    "tcgplayerId": "570405"
  },
  {
    "id": "jp-s5a-peerless-fighters-041/070",
    "name": "Galarian Yamask",
    "supertype": "Pokémon",
    "number": "041/070",
    "rarity": "Common",
    "images": {
      "small": "https://tcgplayer-cdn.tcgplayer.com/product/570406_200w.jpg",
      "large": "https://tcgplayer-cdn.tcgplayer.com/product/570406_400w.jpg"
    },
    "tcgplayerId": "570406"
  },
  {
    "id": "jp-s5a-peerless-fighters-062/070",
    "name": "Braviary",
    "supertype": "Pokémon",
    "number": "062/070",
    "rarity": "Common",
    "images": {
      "small": "https://tcgplayer-cdn.tcgplayer.com/product/570427_200w.jpg",
      "large": "https://tcgplayer-cdn.tcgplayer.com/product/570427_400w.jpg"
    },
    "tcgplayerId": "570427"
  },
  {
    "id": "jp-s5a-peerless-fighters-063/070",
    "name": "Welcoming Lantern",
    "supertype": "Pokémon",
    "number": "063/070",
    "rarity": "Uncommon",
    "images": {
      "small": "https://tcgplayer-cdn.tcgplayer.com/product/570428_200w.jpg",
      "large": "https://tcgplayer-cdn.tcgplayer.com/product/570428_400w.jpg"
    },
    "tcgplayerId": "570428"
  },
  {
    "id": "jp-s5a-peerless-fighters-059/070",
    "name": "Herdier",
    "supertype": "Pokémon",
    "number": "059/070",
    "rarity": "Common",
    "images": {
      "small": "https://tcgplayer-cdn.tcgplayer.com/product/570424_200w.jpg",
      "large": "https://tcgplayer-cdn.tcgplayer.com/product/570424_400w.jpg"
    },
    "tcgplayerId": "570424"
  },
  {
    "id": "jp-s5a-peerless-fighters-030/070",
    "name": "Hatenna",
    "supertype": "Pokémon",
    "number": "030/070",
    "rarity": "Common",
    "images": {
      "small": "https://tcgplayer-cdn.tcgplayer.com/product/570395_200w.jpg",
      "large": "https://tcgplayer-cdn.tcgplayer.com/product/570395_400w.jpg"
    },
    "tcgplayerId": "570395"
  },
  {
    "id": "jp-s5a-peerless-fighters-061/070",
    "name": "Rufflet",
    "supertype": "Pokémon",
    "number": "061/070",
    "rarity": "Common",
    "images": {
      "small": "https://tcgplayer-cdn.tcgplayer.com/product/570426_200w.jpg",
      "large": "https://tcgplayer-cdn.tcgplayer.com/product/570426_400w.jpg"
    },
    "tcgplayerId": "570426"
  },
  {
    "id": "jp-s5a-peerless-fighters-049/070",
    "name": "Spiritomb",
    "supertype": "Pokémon",
    "number": "049/070",
    "rarity": "Uncommon",
    "images": {
      "small": "https://tcgplayer-cdn.tcgplayer.com/product/570414_200w.jpg",
      "large": "https://tcgplayer-cdn.tcgplayer.com/product/570414_400w.jpg"
    },
    "tcgplayerId": "570414"
  },
  {
    "id": "jp-s5a-peerless-fighters-009/070",
    "name": "Larvesta",
    "supertype": "Pokémon",
    "number": "009/070",
    "rarity": "Common",
    "images": {
      "small": "https://tcgplayer-cdn.tcgplayer.com/product/570374_200w.jpg",
      "large": "https://tcgplayer-cdn.tcgplayer.com/product/570374_400w.jpg"
    },
    "tcgplayerId": "570374"
  },
  {
    "id": "jp-s5a-peerless-fighters-033/070",
    "name": "Diglett",
    "supertype": "Pokémon",
    "number": "033/070",
    "rarity": "Common",
    "images": {
      "small": "https://tcgplayer-cdn.tcgplayer.com/product/570398_200w.jpg",
      "large": "https://tcgplayer-cdn.tcgplayer.com/product/570398_400w.jpg"
    },
    "tcgplayerId": "570398"
  },
  {
    "id": "jp-s5a-peerless-fighters-067/070",
    "name": "Klara - 067/070",
    "supertype": "Pokémon",
    "number": "067/070",
    "rarity": "Uncommon",
    "images": {
      "small": "https://tcgplayer-cdn.tcgplayer.com/product/570432_200w.jpg",
      "large": "https://tcgplayer-cdn.tcgplayer.com/product/570432_400w.jpg"
    },
    "tcgplayerId": "570432"
  },
  {
    "id": "jp-s5a-peerless-fighters-050/070",
    "name": "Venipede",
    "supertype": "Pokémon",
    "number": "050/070",
    "rarity": "Common",
    "images": {
      "small": "https://tcgplayer-cdn.tcgplayer.com/product/570415_200w.jpg",
      "large": "https://tcgplayer-cdn.tcgplayer.com/product/570415_400w.jpg"
    },
    "tcgplayerId": "570415"
  },
  {
    "id": "jp-s5a-peerless-fighters-070/070",
    "name": "Dyna Tree Hill",
    "supertype": "Pokémon",
    "number": "070/070",
    "rarity": "Uncommon",
    "images": {
      "small": "https://tcgplayer-cdn.tcgplayer.com/product/570435_200w.jpg",
      "large": "https://tcgplayer-cdn.tcgplayer.com/product/570435_400w.jpg"
    },
    "tcgplayerId": "570435"
  },
  {
    "id": "jp-s5a-peerless-fighters-051/070",
    "name": "Whirlipede",
    "supertype": "Pokémon",
    "number": "051/070",
    "rarity": "Common",
    "images": {
      "small": "https://tcgplayer-cdn.tcgplayer.com/product/570416_200w.jpg",
      "large": "https://tcgplayer-cdn.tcgplayer.com/product/570416_400w.jpg"
    },
    "tcgplayerId": "570416"
  },
  {
    "id": "jp-s5a-peerless-fighters-058/070",
    "name": "Lillipup",
    "supertype": "Pokémon",
    "number": "058/070",
    "rarity": "Common",
    "images": {
      "small": "https://tcgplayer-cdn.tcgplayer.com/product/570423_200w.jpg",
      "large": "https://tcgplayer-cdn.tcgplayer.com/product/570423_400w.jpg"
    },
    "tcgplayerId": "570423"
  },
  {
    "id": "jp-s5a-peerless-fighters-039/070",
    "name": "Boldore",
    "supertype": "Pokémon",
    "number": "039/070",
    "rarity": "Common",
    "images": {
      "small": "https://tcgplayer-cdn.tcgplayer.com/product/570404_200w.jpg",
      "large": "https://tcgplayer-cdn.tcgplayer.com/product/570404_400w.jpg"
    },
    "tcgplayerId": "570404"
  },
  {
    "id": "jp-s5a-peerless-fighters-066/070",
    "name": "Karen's Conviction - 066/070",
    "supertype": "Pokémon",
    "number": "066/070",
    "rarity": "Uncommon",
    "images": {
      "small": "https://tcgplayer-cdn.tcgplayer.com/product/570431_200w.jpg",
      "large": "https://tcgplayer-cdn.tcgplayer.com/product/570431_400w.jpg"
    },
    "tcgplayerId": "570431"
  }
]